statpairviz/__init__.py
statpairviz/annotation.py
statpairviz/version.py
statpairviz-1.0.1.dist-info/AUTHORS.rst
statpairviz-1.0.1.dist-info/LICENSE
statpairviz-1.0.1.dist-info/METADATA
statpairviz-1.0.1.dist-info/WHEEL
statpairviz-1.0.1.dist-info/top_level.txt
statpairviz-1.0.1.dist-info/RECORD
