Metadata-Version: 2.1
Name: statpairviz
Version: 1.0.1
Summary: Helper functions to annotate pairwise comparisons on plots
Author-email: revesansparole <revesansparole@gmail.com>
Maintainer-email: revesansparole <revesansparole@gmail.com>, Jerome Chopard <revesansparole@gmail.com>
License: cc_by_nc
Project-URL: repository, https://gitlab.com/revesansparole/statpairviz
Project-URL: pip, https://pypi.org/project/statpairviz/1.0.1/
Project-URL: conda, https://anaconda.org/revesansparole/statpairviz
Project-URL: doc, https://revesansparole.gitlab.io/statpairviz/
Project-URL: pypi, https://badge.fury.io/py/statpairviz
Classifier: Development Status :: 2 - Pre-Alpha
Classifier: Intended Audience :: Developers
Classifier: License :: OSI Approved :: BSD License
Classifier: Natural Language :: English
Classifier: Programming Language :: Python
Classifier: Programming Language :: Python :: 3
Classifier: Programming Language :: Python :: 3 :: Only
Classifier: Programming Language :: Python :: 3.10
Classifier: Programming Language :: Python :: 3.11
Classifier: Programming Language :: Python :: 3.12
Requires-Python: >=3.10
License-File: LICENSE
License-File: AUTHORS.rst
Provides-Extra: doc
Requires-Dist: sphinx; extra == "doc"
Requires-Dist: sphinx-gallery; extra == "doc"
Requires-Dist: sphinx-rtd-theme; extra == "doc"
Provides-Extra: dvlpt
Requires-Dist: twine; extra == "dvlpt"
Provides-Extra: example
Requires-Dist: matplotlib; extra == "example"
Provides-Extra: test
Requires-Dist: coverage; extra == "test"
Requires-Dist: pytest; extra == "test"
Requires-Dist: pytest-cov; extra == "test"
Requires-Dist: pytest-mock; extra == "test"
